README.rst
setup.py
framework/User.py
framework/__init__.py
framework/gitnotus.py
framework/gitnotus_commandline_utility.py
framework/hook_creator.py
framework/hook_handler.py
framework/hook_handler2.py
framework/json_parser.py
framework/mail_invoker.py
framework/repo_maintainer.py
framework/server.py
framework/user_dict.pkl
framework/webhook_handler.py
gitnotus.egg-info/PKG-INFO
gitnotus.egg-info/SOURCES.txt
gitnotus.egg-info/dependency_links.txt
gitnotus.egg-info/entry_points.txt
gitnotus.egg-info/requires.txt
gitnotus.egg-info/top_level.txt
mail/__init__.py
mail/notification_mail.py
mail/textfile.txt
packaging/__init__.py
usr_bin/__init__.py
usr_bin/gitnotus.py