Metadata-Version: 1.1
Name: gitnotus
Version: 0.1.0
Summary: A high-level Python  CLI for github event management
Home-page: http://dineshappavoo.github.io/gitnotus/
Author: Dinesh Appavoo
Author-email: dinesha.cit@gmail.com
License: MIT
Keywords: event manager
Platform: UNKNOWN
Classifier: Development Status :: 3 - Alpha
Classifier: Intended Audience :: Developers
Classifier: Topic :: Software Development :: Build Tools
Classifier: License :: OSI Approved :: MIT License
Classifier: Programming Language :: Python :: 2
Classifier: Programming Language :: Python :: 2.6
Classifier: Programming Language :: Python :: 2.7
